datatable_faker/__init__.py
datatable_faker-0.1.7.dist-info/LICENSE
datatable_faker-0.1.7.dist-info/METADATA
datatable_faker-0.1.7.dist-info/WHEEL
datatable_faker-0.1.7.dist-info/top_level.txt
datatable_faker-0.1.7.dist-info/RECORD
