Metadata-Version: 2.1
Name: datatable-faker
Version: 0.1.7
Summary: Library to generate fake datatable for unittest 
Home-page: https://github.com/Agent-Hellboy/datatable-faker
Author: Prince Roshan
Author-email: princekrroshan01@gmail.com
License: MIT
Keywords: faker,datatable-faker
Classifier: Programming Language :: Python :: 3.7
Classifier: Programming Language :: Python :: 3.8
Classifier: Programming Language :: Python :: 3.9
Classifier: Programming Language :: Python :: 3.10
Classifier: Programming Language :: Python :: 3.11
Classifier: Operating System :: OS Independent
Requires-Python: >=3.7
License-File: LICENSE
Requires-Dist: faker
